nplinker/__init__.py
nplinker/aa_pred.py
nplinker/aalist.py
nplinker/annotations.py
nplinker/config.py
nplinker/genomics.py
nplinker/genomics_utilities.py
nplinker/loader.py
nplinker/logconfig.py
nplinker/metabolomics.py
nplinker/nplinker.py
nplinker/pickler.py
nplinker/process_output.py
nplinker/spec_clustering.py
nplinker/strains.py
nplinker/utils.py
nplinker/class_info/__init__.py
nplinker/class_info/chem_classes.py
nplinker/class_info/class_matches.py
nplinker/class_info/runcanopus.py
nplinker/data/MIBiG2.0_compounds_with_AS_BGC_CF_NPC_classes.txt
nplinker/data/matched_mibig_gnps_update.csv
nplinker/data/matched_mibig_gnps_update.mgf
nplinker/data/nplinker.toml
nplinker/data/strain_id_mapping.csv
nplinker/pairedomics/__init__.py
nplinker/pairedomics/downloader.py
nplinker/pairedomics/runbigscape.py
nplinker/parsers/__init__.py
nplinker/parsers/kcb.py
nplinker/parsers/mgf.py
nplinker/scoring/IOKR.py
nplinker/scoring/__init__.py
nplinker/scoring/data_linking.py
nplinker/scoring/data_linking_functions.py
nplinker/scoring/methods.py
nplinker/scoring/misc.py
nplinker/scoring/iokr/__init__.py
nplinker/scoring/iokr/build_input_matrix.py
nplinker/scoring/iokr/build_test_matrix.py
nplinker/scoring/iokr/formula.py
nplinker/scoring/iokr/iokr.py
nplinker/scoring/iokr/iokr_opt.py
nplinker/scoring/iokr/iokrdata.py
nplinker/scoring/iokr/mk_fprints.py
nplinker/scoring/iokr/nplinker_iokr.py
nplinker/scoring/iokr/run_iokr.py
nplinker/scoring/iokr/run_iokr_novel.py
nplinker/scoring/iokr/spectrum.py
nplinker/scoring/iokr/spectrum_filters.py
nplinker/scoring/rosetta/__init__.py
nplinker/scoring/rosetta/rosetta.py
nplinker/scoring/rosetta/rosetta_functions.py
nplinker/scoring/rosetta/spec_lib.py
nplinker-1.3.2.data/scripts/install-nplinker-deps
nplinker-1.3.2.dist-info/LICENSE
nplinker-1.3.2.dist-info/METADATA
nplinker-1.3.2.dist-info/NOTICE
nplinker-1.3.2.dist-info/WHEEL
nplinker-1.3.2.dist-info/top_level.txt
nplinker-1.3.2.dist-info/RECORD
