Metadata-Version: 2.1
Name: nplinker
Version: 1.3.2
Summary: Natural Products Linker
License: Apache-2.0 license
Project-URL: Homepage, https://github.com/NPLinker/nplinker
Project-URL: Bug Tracker, https://github.com/NPLinker/nplinker/issues
Keywords: Genome,Metabolome,Natural Products,Data Mining
Classifier: Development Status :: 4 - Beta
Classifier: Intended Audience :: Education
Classifier: Intended Audience :: Science/Research
Classifier: License :: OSI Approved :: Apache Software License
Classifier: Natural Language :: English
Classifier: Operating System :: MacOS
Classifier: Operating System :: POSIX :: Linux
Classifier: Programming Language :: Python :: 3
Classifier: Programming Language :: Python :: 3.7
Classifier: Programming Language :: Python :: 3.8
Classifier: Programming Language :: Python :: 3.9
Classifier: Programming Language :: Python :: 3.10
Requires-Python: >=3.7
License-File: LICENSE
Requires-Dist: beautifulsoup4
Requires-Dist: biopython
Requires-Dist: httpx
Requires-Dist: numpy
Requires-Dist: pandas
Requires-Dist: progress
Requires-Dist: scipy
Requires-Dist: sortedcontainers
Requires-Dist: toml
Requires-Dist: xdg
Provides-Extra: dev
Requires-Dist: bump2version ; extra == 'dev'
Requires-Dist: coverage[toml] ; extra == 'dev'
Requires-Dist: isort ; extra == 'dev'
Requires-Dist: prospector[with_pyroma] ; extra == 'dev'
Requires-Dist: pytest ; extra == 'dev'
Requires-Dist: pytest-cov ; extra == 'dev'
Requires-Dist: sphinx ; extra == 'dev'
Requires-Dist: sphinx-rtd-theme ; extra == 'dev'
Requires-Dist: sphinx-autoapi ; extra == 'dev'
Requires-Dist: myst-parser ; extra == 'dev'
Requires-Dist: unimport ; extra == 'dev'
Requires-Dist: yapf ; extra == 'dev'
Provides-Extra: publishing
Requires-Dist: build ; extra == 'publishing'
Requires-Dist: wheel ; extra == 'publishing'
